pipincluder/__init__.py
pipincluder-1.0.6.dist-info/License
pipincluder-1.0.6.dist-info/METADATA
pipincluder-1.0.6.dist-info/WHEEL
pipincluder-1.0.6.dist-info/top_level.txt
pipincluder-1.0.6.dist-info/RECORD
