Metadata-Version: 2.1
Name: pipincluder
Version: 1.0.6
Summary: To import packages if they are found, or download them from pypi if they are not present.This project is in order to bypass errors during importing any package.
Home-page: https://github.com/yasserbdj96/pipincluder
Author: Yasser Bdj (Boudjada Yasser)
Author-email: yasser.bdj96@gmail.com
License: MIT License
Project-URL: Author WebSite, https://yasserbdj96.github.io/
Keywords: yasserbdj96,python,pipincluder,for,import,packages,without,errors,of,unavailability.,To,import,packages,if,they,are,found,,or,download,them,from,pypi,if,they,are,not,present.This,project,is,in,order,to,bypass,errors,during,importing,any,package.
Platform: UNKNOWN
Classifier: Development Status :: 5 - Production/Stable
Classifier: Intended Audience :: Developers
Classifier: License :: OSI Approved :: MIT License
Classifier: Programming Language :: Python :: 3
Classifier: Operating System :: Unix
Classifier: Operating System :: MacOS :: MacOS X
Classifier: Operating System :: Microsoft :: Windows
Classifier: Topic :: Software Development :: Build Tools
Classifier: Topic :: Software Development :: Libraries :: Python Modules
Classifier: Topic :: Communications :: Email
Requires-Python: >=3.x.x
